{
    "manifest_version": "0.1.0",
    "generated_by": "scripts/verificationsemanticgen.sh",
    "subject": "verify:daemon",
    "source": "lisp/agent/verification.lisp",
    "algorithm": "sha256",
    "hashes": [
        {
            "id": "semantic:verification-graph",
            "source": "docs/generated/verification-evidence.json",
            "fields": [
                "form",
                "ontology_chain",
                "verification_nodes",
                "generated_backends"
            ],
            "meaning": "Verification graph shape and generated backend contract.",
            "hash": "6f2d54b1a95ced56b143140df40e877e4bb17822969b75452bee873d4e1dfc07"
        },
        {
            "id": "semantic:codegen-map",
            "source": "docs/generated/verification-codegen.json",
            "fields": [
                "axes"
            ],
            "meaning": "Ontology codegen axes mapped to generated backends.",
            "hash": "f61074232ef9b2300b065b59413565a64ea9507e40d4f5f1276cecde18a68ddd"
        },
        {
            "id": "semantic:loss-ledger",
            "source": "docs/generated/verification-loss-ledger.json",
            "fields": [
                "ledger"
            ],
            "meaning": "Declared adapter translation loss without forbidden L4 loss.",
            "hash": "f9db22577ae6810e01e7807c11dd4f1947955825dfbc1fc0a74ba2a80a3b2714"
        },
        {
            "id": "semantic:conformance",
            "source": "docs/generated/verification-conformance.json",
            "fields": [
                "rules"
            ],
            "meaning": "Required checks for generated backend freshness.",
            "hash": "dd276764fbd4fad29533d0f2be7de429403e0a8d68917fe0b15677101231cff4"
        },
        {
            "id": "semantic:authority",
            "source": "docs/generated/verification-authority.json",
            "fields": [
                "authority_profile",
                "decisions",
                "closure_rules"
            ],
            "meaning": "Governance authority gate and review decision contract.",
            "hash": "68ecf4f3781eaef07de93c9566592192d4e337b068d986a972621524f31d95ed"
        }
    ],
    "closure_rules": [
        {
            "id": "semantic:hash-recomputes",
            "meaning": "Every semantic hash recomputes from source fields.",
            "check": "scripts/verificationsemanticgen.sh check"
        },
        {
            "id": "semantic:source-exists",
            "meaning": "Every semantic hash source is generated evidence.",
            "check": "scripts/verificationsemanticgen.sh check"
        },
        {
            "id": "semantic:stable-canonical-json",
            "meaning": "Hash input uses sorted canonical JSON.",
            "check": "scripts/verificationsemanticgen.sh check"
        }
    ]
}
